setup.py
tilepaper/__init__.py
tilepaper/cli.py
tilepaper/config.py
tilepaper/grid.py
tilepaper/image.py
tilepaper/renderer.py
tilepaper/tiler.py
tilepaper.egg-info/PKG-INFO
tilepaper.egg-info/SOURCES.txt
tilepaper.egg-info/dependency_links.txt
tilepaper.egg-info/entry_points.txt
tilepaper.egg-info/not-zip-safe
tilepaper.egg-info/requires.txt
tilepaper.egg-info/top_level.txt