Metadata-Version: 1.1
Name: tilepaper
Version: 0.1.12
Summary: Generate OS/X "Shifting Tiles" style wallpapers
Home-page: https://www.codedog.co.uk/tilepaper
Author: Sam Rudge
Author-email: sam@codesam.co.uk
License: MIT
Platform: UNKNOWN
Classifier: Environment :: Console
Classifier: Intended Audience :: End Users/Desktop
Classifier: License :: OSI Approved :: MIT License
Classifier: Topic :: Multimedia :: Graphics
Classifier: Topic :: Utilities
Classifier: Programming Language :: Python
Classifier: Programming Language :: Python :: 2
Classifier: Programming Language :: Python :: 2.7
Classifier: Programming Language :: Python :: 3
Classifier: Programming Language :: Python :: 3.3
Classifier: Programming Language :: Python :: 3.4
Classifier: Programming Language :: Python :: 3.5
